discussionset/__init__.py
discussionset/data/Screenshot_20230502_021209.jpg
discussionset/data/《中西医精神心理疾病汇通》序终结版本.pdf
discussionset/data/以辩证看待取代消灭极端认知的方法论.pdf
discussionset/data/修改中_高考制度之下恶性竞争的教育模式.docx
discussionset/data/修改结束高考制度之下恶性竞争的教育模式_20221031080200.pdf
discussionset/data/情志干预在疾病中的作用.pdf
discussionset/data/我谈中医情志学.pdf
discussionset/data/投稿 以辩证看待取代消灭极端认知的方法论.docx
discussionset/data/投稿 以辩证看待取代消灭极端认知的方法论.pdf
discussionset/data/稿件上传错误，请否决该投稿申请.doc
discussionset/data/稿件上传错误，请否决该投稿申请.pdf
discussionset/data/精神心理疾病带来的巨大挑战.pdf
discussionset/data/精神心理疾病带来的巨大挑战最终稿.docx
discussionset/data/精神心理疾病带来的巨大挑战最终稿投稿无瑕疵再修改最终投稿.doc
discussionset/data/精神心理疾病带来的巨大挑战最终稿投稿无瑕疵再修改最终投稿.pdf
discussionset/data/终结 为什么只有中国能真正意义上的有效控制疫情.docx
discussionset/data/终结 为什么只有中国能真正意义上的有效控制疫情.pdf
discussionset/data/隐藏论视角下精神心理疾病带来的.docx
discussionset/data/隐藏论视角下精神心理疾病带来的.pdf
discussionset-0.0.1.dist-info/licenses/LICENSE
discussionset-0.0.1.dist-info/METADATA
discussionset-0.0.1.dist-info/WHEEL
discussionset-0.0.1.dist-info/top_level.txt
discussionset-0.0.1.dist-info/RECORD
